holoext/__init__.py
holoext/bokeh.py
holoext/utils.py
holoext/xbokeh.py
holoext/data/__init__.py
holoext/data/ncl_cmap_names.py
holoext/data/ncl_cmaps.pkl
holoext/data/__pycache__/__init__.cpython-36.pyc
holoext/data/__pycache__/ncl_cmap_names.cpython-36.pyc
holoext-1.0.4.dist-info/METADATA
holoext-1.0.4.dist-info/RECORD
holoext-1.0.4.dist-info/WHEEL
holoext-1.0.4.dist-info/top_level.txt
