Metadata-Version: 2.1
Name: holoext
Version: 1.0.4
Summary: Holoviews Extension
Home-page: http://github.com/ahuang11/holoext
Author: Andrew Huang
Author-email: huang.andrew12@gmail.com
License: MIT
Keywords: data,visualization,holoviews,bokeh,mod,extension,andrew,huang
Platform: UNKNOWN
Requires-Dist: matplotlib
Requires-Dist: numpy
Requires-Dist: pandas
Requires-Dist: holoviews
Requires-Dist: bokeh
Requires-Dist: dask
